AUTHORS.rst
CHANGES.rst
LICENSE
MANIFEST.in
README.rst
setup.py
tox.ini
update_cpp.sh
DAWG_Patched.egg-info/PKG-INFO
DAWG_Patched.egg-info/SOURCES.txt
DAWG_Patched.egg-info/dependency_links.txt
DAWG_Patched.egg-info/top_level.txt
docs/Makefile
docs/conf.py
docs/index.rst
docs/make.bat
lib/COPYING
lib/b64/cdecode.c
lib/b64/cdecode.h
lib/b64/cencode.c
lib/b64/cencode.h
lib/b64/decode.h
lib/b64/encode.h
lib/dawgdic/base-types.h
lib/dawgdic/base-unit.h
lib/dawgdic/bit-pool.h
lib/dawgdic/completer.h
lib/dawgdic/dawg-builder.h
lib/dawgdic/dawg-unit.h
lib/dawgdic/dawg.h
lib/dawgdic/dictionary-builder.h
lib/dawgdic/dictionary-extra-unit.h
lib/dawgdic/dictionary-unit.h
lib/dawgdic/dictionary.h
lib/dawgdic/guide-builder.h
lib/dawgdic/guide-unit.h
lib/dawgdic/guide.h
lib/dawgdic/link-table.h
lib/dawgdic/object-pool.h
lib/dawgdic/ranked-completer-candidate.h
lib/dawgdic/ranked-completer-node.h
lib/dawgdic/ranked-completer.h
lib/dawgdic/ranked-guide-builder.h
lib/dawgdic/ranked-guide-link.h
lib/dawgdic/ranked-guide-unit.h
lib/dawgdic/ranked-guide.h
src/_base_types.cpp
src/_base_types.pxd
src/_completer.cpp
src/_completer.pxd
src/_dawg.cpp
src/_dawg.pxd
src/_dawg_builder.cpp
src/_dawg_builder.pxd
src/_dictionary.cpp
src/_dictionary.pxd
src/_dictionary_builder.cpp
src/_dictionary_builder.pxd
src/_dictionary_unit.cpp
src/_dictionary_unit.pxd
src/_guide.cpp
src/_guide.pxd
src/_guide_builder.cpp
src/_guide_builder.pxd
src/_guide_unit.cpp
src/_guide_unit.pxd
src/b64_decode.cpp
src/b64_decode.pxd
src/dawg.cpp
src/dawg.pyx
src/iostream.cpp
src/iostream.pxd
tests/__init__.py
tests/test_dawg.py
tests/test_payload_dawg.py
tests/test_prediction.py